Metadata-Version: 1.0
Name: mp2020-distributions
Version: 0.1
Summary: Gaussian and Binomial distributions
Home-page: UNKNOWN
Author: Michael Parravani
Author-email: michael.parravani@gmail.com
License: UNKNOWN
Platform: UNKNOWN
